src/__init__.py
src/__main__.py
src/cli.py
src/frame_dispatcher.py
src/processors/__init__.py
src/processors/csv_gzip_writer.py
src/trackers/__init__.py
src/trackers/mediapipe_face.py
src/trackers/mediapipe_hand.py
src/trackers/mediapipe_pose.py
trucotrack-0.0.5.dist-info/LICENSE.txt
trucotrack-0.0.5.dist-info/METADATA
trucotrack-0.0.5.dist-info/WHEEL
trucotrack-0.0.5.dist-info/entry_points.txt
trucotrack-0.0.5.dist-info/top_level.txt
trucotrack-0.0.5.dist-info/RECORD
