Metadata-Version: 2.1
Name: trucotrack
Version: 0.0.5
Summary: Generate data files from captured motion
Home-page: UNKNOWN
Author: Carlos Capote Pérez-Andreu
Author-email: <carlos.capote@hawara.es>
License: UNKNOWN
Keywords: python,motion,motion capture,video,stream,video stream,camera stream
Platform: UNKNOWN
Classifier: Development Status :: 1 - Planning
Classifier: Intended Audience :: Developers
Classifier: Programming Language :: Python :: 3
Classifier: Operating System :: Unix
Classifier: Operating System :: MacOS :: MacOS X
Classifier: Operating System :: Microsoft :: Windows
License-File: LICENSE.txt
Requires-Dist: mediapipe
Requires-Dist: opencv-python
